agentrun/__init__.py
agentrun-0.2.5.dist-info/LICENSE
agentrun-0.2.5.dist-info/METADATA
agentrun-0.2.5.dist-info/WHEEL
agentrun-0.2.5.dist-info/top_level.txt
agentrun-0.2.5.dist-info/RECORD
