Metadata-Version: 2.1
Name: agentrun
Version: 0.2.5
Summary: The easiest way to run AI or user generated python code safely in a docker container
Author-email: Jonathan Adly <gadly0123@gmail.com>
License: Apache-2.0
Project-URL: Homepage, https://github.com/jonathan-adly/agentrun
Project-URL: Changelog, https://github.com/jonathan-adly/agentrun/releases
Project-URL: Issues, https://github.com/jonathan-adly/agentrun/issues
Project-URL: CI, https://github.com/jonathan-adly/agentrun/actions
Classifier: License :: OSI Approved :: Apache Software License
Requires-Python: >=3.10
License-File: LICENSE
Requires-Dist: docker
Requires-Dist: RestrictedPython
Provides-Extra: test
Requires-Dist: pytest; extra == "test"
Requires-Dist: pytest-cov; extra == "test"
Requires-Dist: pytest-benchmark; extra == "test"
Requires-Dist: mypy; extra == "test"
Requires-Dist: mkdocs; extra == "test"
Requires-Dist: mkdocs-material; extra == "test"
Requires-Dist: mkdocstrings[python]; extra == "test"
Requires-Dist: mkdocs-jupyter; extra == "test"
